{
  "title": "PythonStuff",
  "author": "Joey00072",
  "headerTitle": "PythonStuff",
  "description": "Everything python",
  "language": "en-us",
  "siteUrl": "https://pythonstuff.com",
  "siteRepo": "https://github.com/joey00072/Pythonstuff",
  "image": "/static/images/me.png",
  "socialBanner": "/static/images/twitter-card.png",
  "email": "00Shxf@gmail.com",
  "github": "https://github.com/joey00072",
  "twitter": "https://twitter.com/shxf0072",
  "facebook": "https://www.instagram.com/_.shxf_/",
  "youtube": "https://www.youtube.com/channel/UC3lb-XnKpjUMHG_vwDNMJ5w",
  "linkedin": "#",
  "locale": "en-US"
}
